tinydictdb/__init__.py
tinydictdb/tinydictdb.py
tinydictdb/prettyprinter.py
tinydictdb-1.3.2.dist-info/METADATA
tinydictdb-1.3.2.dist-info/top_level.txt
tinydictdb-1.3.2.dist-info/DESCRIPTION.rst
tinydictdb-1.3.2.dist-info/pbr.json
tinydictdb-1.3.2.dist-info/WHEEL
tinydictdb-1.3.2.dist-info/RECORD
tinydictdb-1.3.2.dist-info/metadata.json
