Metadata-Version: 2.0
Name: tinydictdb
Version: 1.3.2
Summary: A tiny flat file (JSON/YAML) dictionnaries database.
Home-page: https://github.com/sl4shme/tinydictdb
Author: Pierre-Arthur MATHIEU
Author-email: pi3rra@root.gg
License: Apache Software License
Keywords: json database yaml dict dictionnary
Platform: UNKNOWN
Classifier: Development Status :: 3 - Alpha
Classifier: Intended Audience :: Developers
Classifier: Topic :: Database
Classifier: License :: OSI Approved :: Apache Software License
Classifier: Programming Language :: Python :: 2.6
Classifier: Programming Language :: Python :: 2.7
Classifier: Programming Language :: Python :: 3.3
